sp_licitacoesPy/__init__.py
sp_licitacoesPy/licitacoes.py
sp_licitacoesPy-0.0.2.dist-info/LICENSE
sp_licitacoesPy-0.0.2.dist-info/METADATA
sp_licitacoesPy-0.0.2.dist-info/WHEEL
sp_licitacoesPy-0.0.2.dist-info/top_level.txt
sp_licitacoesPy-0.0.2.dist-info/RECORD
