Metadata-Version: 2.1
Name: sp-licitacoesPy
Version: 0.0.2
Summary: Simples wrapper para API de licitações da Prefeitura de São Paulo
Home-page: https://github.com/PzanettiD/sp_licitacoesPy
Author: PzanettiD
Author-email: zanetti.pepe@gmail.com
License: UNKNOWN
Platform: UNKNOWN
Classifier: Programming Language :: Python :: 3
Classifier: License :: OSI Approved :: MIT License
Classifier: Operating System :: OS Independent
Requires-Python: >=3.6
